hyperutils/__init__.py
hyperutils/can_access_resource.py
hyperutils/can_access_resource_with_token.py
hyperutils/hyperbloq_jwt.py
hyperutils/models/__init__.py
hyperutils/models/py_object_id_field.py
hyperutils/models/user.py
hyperutils/verify_access_token.py
hyperutils-0.1.9.dist-info/WHEEL
hyperutils-0.1.9.dist-info/METADATA
hyperutils-0.1.9.dist-info/RECORD
