Metadata-Version: 2.1
Name: hyperutils
Version: 0.1.9
Summary: hyperbloq-utils
Author: Lionel Cuevas
Author-email: lionel.c@hyperbloq.com
Requires-Python: >=3.8,<4.0
Classifier: Programming Language :: Python :: 3
Classifier: Programming Language :: Python :: 3.10
Classifier: Programming Language :: Python :: 3.8
Classifier: Programming Language :: Python :: 3.9
Requires-Dist: PyJWT[crypto] (>=2.4.0,<3.0.0)
Requires-Dist: fastapi
Requires-Dist: pydantic[email] (>=1.9.1,<2.0.0)
Requires-Dist: pymongo (>=4.1.1,<5.0.0)
